offensive_azure/Access_Tokens/README.md
offensive_azure/Access_Tokens/read_token.py
offensive_azure/Access_Tokens/requirements.txt
offensive_azure/Access_Tokens/token_juggle.py
offensive_azure/Azure_AD/README.md
offensive_azure/Azure_AD/get_tenant.py
offensive_azure/Azure_AD/get_users.py
offensive_azure/Azure_AD/requirements.txt
offensive_azure/Device_Code/README.md
offensive_azure/Device_Code/device_code_easy_mode.py
offensive_azure/Device_Code/requirements.txt
offensive_azure/Outsider_Recon/README.md
offensive_azure/Outsider_Recon/outsider_recon.py
offensive_azure/Outsider_Recon/requirements.txt
offensive_azure/User_Enum/README.md
offensive_azure/User_Enum/requirements.txt
offensive_azure/User_Enum/user_enum.py
offensive_azure/__init__.py
offensive_azure-0.48.dist-info/entry_points.txt
offensive_azure-0.48.dist-info/LICENSE
offensive_azure-0.48.dist-info/WHEEL
offensive_azure-0.48.dist-info/METADATA
offensive_azure-0.48.dist-info/RECORD
