Metadata-Version: 2.1
Name: offensive-azure
Version: 0.48
Summary: Collection of tools for attacking Microsoft Cloud products
Home-page: https://github.com/blacklanternsecurity.com/offensive-azure
License: GPL-3.0
Author: Cody Martin
Author-email: debifrank00@gmail.com
Requires-Python: >=3.8,<4.0
Classifier: License :: OSI Approved :: GNU General Public License v3 (GPLv3)
Classifier: Programming Language :: Python :: 3
Classifier: Programming Language :: Python :: 3.10
Classifier: Programming Language :: Python :: 3.8
Classifier: Programming Language :: Python :: 3.9
Requires-Dist: colorama (>=0.4.4,<0.5.0)
Requires-Dist: dnspython (>=2.2.1,<3.0.0)
Requires-Dist: pycryptodome (>=3.14.1,<4.0.0)
Requires-Dist: python-whois (>=0.7.3,<0.8.0)
Requires-Dist: requests (>=2.27.1,<3.0.0)
Requires-Dist: uuid (>=1.30,<2.0)
Project-URL: Repository, https://github.com/blacklanternsecurity.com/offensive-azure
